{
  "AA": "6",
  "AC": "1",
  "CY": "DE",
  "DD": null,
  "DI": "2014/24/EU",
  "DS": "2019-12-29",
  "DT": null,
  "MA": "B",
  "NC": "1",
  "ND": "000050-2020",
  "OC": [
    "45000000",
    "45200000",
    "45210000",
    "45215000",
    "45215200",
    "45215210",
    "45215214"
  ],
  "OJ": "001/2020",
  "OL": "de",
  "OY": [
    "DE",
    "DEG",
    "DEG0",
    "DEG01"
  ],
  "PC": [
    "45000000",
    "45200000",
    "45210000",
    "45215000",
    "45215200",
    "45215210",
    "45215214"
  ],
  "PD": "2020-01-02",
  "PR": "1",
  "RC": [
    "DE",
    "DEG",
    "DEG0",
    "DEG01"
  ],
  "RN": 2017144335,
  "RP": "5",
  "TD": "7",
  "TVH": "709130.00",
  "TVL": "709130.00",
  "TY": "9"
}